docs/conf.py
examples/iterative_refinement_utils.py
qhdopt/__init__.py
qhdopt/_version.py
qhdopt/qhd.py
qhdopt/qhd_base.py
qhdopt/response.py
qhdopt/backend/__init__.py
qhdopt/backend/backend.py
qhdopt/backend/baseline_backend.py
qhdopt/backend/dwave_backend.py
qhdopt/backend/ionq_backend.py
qhdopt/backend/qutip_backend.py
qhdopt/utils/__init__.py
qhdopt/utils/benchmark_utils.py
qhdopt/utils/decoding_utils.py
qhdopt/utils/function_preprocessing_utils.py
tests/test_qhd.py
qhdopt-0.0.1.dist-info/LICENSE
qhdopt-0.0.1.dist-info/METADATA
qhdopt-0.0.1.dist-info/WHEEL
qhdopt-0.0.1.dist-info/top_level.txt
qhdopt-0.0.1.dist-info/RECORD
