Metadata-Version: 2.1
Name: qhdopt
Version: 0.0.1
Summary: A software package for nonconvex optimization with quantum devices.
Classifier: Development Status :: 2 - Pre-Alpha
Classifier: Intended Audience :: Science/Research
Classifier: Natural Language :: English
Classifier: Programming Language :: Python
Classifier: Programming Language :: Python :: 3.9
Classifier: Programming Language :: Python :: 3.10
Classifier: Programming Language :: Python :: 3.11
License-File: LICENSE
Requires-Dist: jax[cpu]
Requires-Dist: sympy
Requires-Dist: scipy <1.12,>=1.10.1
Requires-Dist: numpy <1.28.0
Requires-Dist: jaxlib
Requires-Dist: qutip
Requires-Dist: simuq
Requires-Dist: dwave-system
Requires-Dist: qiskit
Provides-Extra: all
Requires-Dist: qhdopt[dev] ; extra == 'all'
Provides-Extra: dev
Requires-Dist: tox ; extra == 'dev'
